<xml xmlns="http://www.w3.org/1999/xhtml">
  <block type="variables_set" id="1" inline="true" x="-8" y="-1815">
    <field name="VAR">lena</field>
    <value name="VALUE">
      <block type="imread" id="2">
        <field name="grey">FALSE</field>
        <field name="filename">media/blockly0.png</field>
      </block>
    </value>
    <next>
      <block type="variables_set" id="3" inline="true">
        <field name="VAR">bin</field>
        <value name="VALUE">
          <block type="threshold" id="4" inline="false">
            <field name="thresh_val">30</field>
            <field name="thresh_to">255</field>
            <field name="flag">cv2.THRESH_OTSU</field>
            <value name="img">
              <block type="cvtcolor" id="5" inline="false">
                <field name="flag">cv2.COLOR_BGR2GRAY</field>
                <value name="img">
                  <block type="variables_get" id="6">
                    <field name="VAR">lena</field>
                  </block>
                </value>
              </block>
            </value>
          </block>
        </value>
        <next>
          <block type="imshow" id="7" inline="false">
            <field name="windowname">binwin</field>
            <value name="image">
              <block type="variables_get" id="8">
                <field name="VAR">bin</field>
              </block>
            </value>
            <next>
              <block type="variables_set" id="9" inline="true">
                <field name="VAR">contours</field>
                <value name="VALUE">
                  <block type="findcontours" id="10" inline="false">
                    <field name="mode">cv2.RETR_LIST</field>
                    <field name="approx">cv2.CHAIN_APPROX_TC89_KCOS</field>
                    <value name="img">
                      <block type="variables_get" id="11">
                        <field name="VAR">bin</field>
                      </block>
                    </value>
                  </block>
                </value>
                <next>
                  <block type="controls_forEach" id="12" inline="false">
                    <field name="VAR">cont</field>
                    <value name="LIST">
                      <block type="variables_get" id="13">
                        <field name="VAR">contours</field>
                      </block>
                    </value>
                    <statement name="DO">
                      <block type="controls_if" id="56" inline="false">
                        <value name="IF0">
                          <block type="logic_compare" id="89" inline="true">
                            <field name="OP">GT</field>
                            <value name="A">
                              <block type="contourarea" id="90" inline="false">
                                <value name="contour">
                                  <block type="variables_get" id="91">
                                    <field name="VAR">cont</field>
                                  </block>
                                </value>
                              </block>
                            </value>
                            <value name="B">
                              <block type="math_number" id="92">
                                <field name="NUM">50</field>
                              </block>
                            </value>
                          </block>
                        </value>
                        <statement name="DO0">
                          <block type="variables_set" id="14" inline="true">
                            <field name="VAR">rect</field>
                            <value name="VALUE">
                              <block type="boundingrect" id="15" inline="false">
                                <value name="contour">
                                  <block type="variables_get" id="16">
                                    <field name="VAR">cont</field>
                                  </block>
                                </value>
                              </block>
                            </value>
                            <next>
                              <block type="rectangle" id="17" inline="false">
                                <value name="image">
                                  <block type="variables_get" id="18">
                                    <field name="VAR">lena</field>
                                  </block>
                                </value>
                                <value name="tl">
                                  <block type="point_tl" id="19" inline="false">
                                    <value name="rect">
                                      <block type="variables_get" id="20">
                                        <field name="VAR">rect</field>
                                      </block>
                                    </value>
                                  </block>
                                </value>
                                <value name="br">
                                  <block type="point_br" id="21" inline="false">
                                    <value name="rect">
                                      <block type="variables_get" id="22">
                                        <field name="VAR">rect</field>
                                      </block>
                                    </value>
                                  </block>
                                </value>
                                <value name="color">
                                  <block type="colour_picker" id="23">
                                    <field name="COLOUR">#66cccc</field>
                                  </block>
                                </value>
                              </block>
                            </next>
                          </block>
                        </statement>
                      </block>
                    </statement>
                    <next>
                      <block type="imshow" id="24" inline="false">
                        <field name="windowname">mywin</field>
                        <value name="image">
                          <block type="variables_get" id="25">
                            <field name="VAR">lena</field>
                          </block>
                        </value>
                        <next>
                          <block type="waitkey" id="26">
                            <field name="millis">0</field>
                            <field name="key">27</field>
                          </block>
                        </next>
                      </block>
                    </next>
                  </block>
                </next>
              </block>
            </next>
          </block>
        </next>
      </block>
    </next>
  </block>
</xml>